neidspecmatch/__init__.py
neidspecmatch/bary.py
neidspecmatch/bin_spectra.py
neidspecmatch/config.py
neidspecmatch/library.py
neidspecmatch/likelihood.py
neidspecmatch/neid_archive.py
neidspecmatch/neidspecmatch.py
neidspecmatch/plot.py
neidspecmatch/priors.py
neidspecmatch/rotbroad_help.py
neidspecmatch/run.py
neidspecmatch/target.py
neidspecmatch/utils.py
neidspecmatch/version.py
neidspecmatch/vsini_limit.py
neidspecmatch/data/.DS_Store
neidspecmatch/data/target_files/TIC 437039407.config
neidspecmatch-0.1.4.dist-info/METADATA
neidspecmatch-0.1.4.dist-info/WHEEL
neidspecmatch-0.1.4.dist-info/top_level.txt
neidspecmatch-0.1.4.dist-info/RECORD
