Metadata-Version: 2.2
Name: neidspecmatch
Version: 0.1.4
Summary: Matching NEID Spectra
Home-page: https://github.com/gummiks/hpfspecmatch/
Author: Te Han, Gudmundur Stefansson (author of HPFSpecMatch)
Author-email: tehanhunter@gmail.com
Keywords: NEID Spectra Astronomy
Classifier: License :: OSI Approved :: MIT License
Classifier: Topic :: Scientific/Engineering :: Astronomy
Requires-Dist: numpy==1.24.3
Requires-Dist: numba
Requires-Dist: pytransit
Requires-Dist: numpy
Requires-Dist: barycorrpy
Requires-Dist: emcee
Requires-Dist: lmfit
Requires-Dist: neidspec
Requires-Dist: crosscorr
Requires-Dist: astroquery==0.4.7
Requires-Dist: glob2
Requires-Dist: celerite
Requires-Dist: radvel
Requires-Dist: wget
Requires-Dist: siphash24
Dynamic: author
Dynamic: author-email
Dynamic: classifier
Dynamic: description
Dynamic: description-content-type
Dynamic: home-page
Dynamic: keywords
Dynamic: requires-dist
Dynamic: summary
